{
    "stepTypes": [
        {
            "@type-id": "custom.CategoryAssignment",
            "@supports-parallel-execution": "false",
            "@supports-site-context": "true",
            "@supports-organization-context": "false",
            "module": "cartridges/app_storefront_custom/cartridge/scripts/job/CategoryAssignment.js",
            "function": "execute",
            "transactional": "true",
            "parameters": {
                "parameter": [
                    {
                        "@name": "brand",
                        "@type": "string",
                        "@required": "true"
                    },
                    {
                        "@name": "categoryID",
                        "@type": "string",
                        "@required": "true"
                    },
                    {
                        "@name": "catalogID",
                        "@type": "string",
                        "@required": "true"
                    }
                ]
            },
            "status-codes": {
                "status": [
                    {
                        "@code": "ERROR"
                    },
                    {
                        "@code": "OK"
                    }
                ]
            }
        },
        {
            "@type-id": "custom.TestJob",
            "@supports-parallel-execution": "false",
            "@supports-site-context": "true",
            "@supports-organization-context": "false",
            "module": "cartridges/app_storefront_custom/cartridge/scripts/job/TestJobModule.js",
            "function": "execute",
            "transactional": "true",
            "parameters": {
                "parameter": [
                    {
                        "@name": "firstParam",
                        "@type": "string",
                        "@required": "true"
                    },
                    {
                        "@name": "secondParam",
                        "@type": "string",
                        "@required": "true"
                    },
                    {
                        "@name": "thirdParam",
                        "@type": "string",
                        "@required": "true"
                    }
                ]
            },
            "status-codes": {
                "status": [
                    {
                        "@code": "ERROR"
                    },
                    {
                        "@code": "OK"
                    }
                ]
            }
        }
    ]
}
